alibabacloud_energyexpertexternal20220923/__init__.py
alibabacloud_energyexpertexternal20220923/client.py
alibabacloud_energyexpertexternal20220923/models/__init__.py
alibabacloud_energyexpertexternal20220923/models/_add_folder_request.py
alibabacloud_energyexpertexternal20220923/models/_add_folder_response.py
alibabacloud_energyexpertexternal20220923/models/_add_folder_response_body.py
alibabacloud_energyexpertexternal20220923/models/_analyze_vl_realtime_advance_request.py
alibabacloud_energyexpertexternal20220923/models/_analyze_vl_realtime_request.py
alibabacloud_energyexpertexternal20220923/models/_analyze_vl_realtime_response.py
alibabacloud_energyexpertexternal20220923/models/_analyze_vl_realtime_response_body.py
alibabacloud_energyexpertexternal20220923/models/_batch_save_instruction_status_request.py
alibabacloud_energyexpertexternal20220923/models/_batch_save_instruction_status_response.py
alibabacloud_energyexpertexternal20220923/models/_batch_save_instruction_status_response_body.py
alibabacloud_energyexpertexternal20220923/models/_batch_update_system_running_plan_request.py
alibabacloud_energyexpertexternal20220923/models/_batch_update_system_running_plan_response.py
alibabacloud_energyexpertexternal20220923/models/_batch_update_system_running_plan_response_body.py
alibabacloud_energyexpertexternal20220923/models/_carbon_emission_elec_summary_item.py
alibabacloud_energyexpertexternal20220923/models/_chat_document_page_num.py
alibabacloud_energyexpertexternal20220923/models/_chat_folder_item.py
alibabacloud_energyexpertexternal20220923/models/_chat_item.py
alibabacloud_energyexpertexternal20220923/models/_chat_ref_doc_info.py
alibabacloud_energyexpertexternal20220923/models/_chat_ref_doc_item.py
alibabacloud_energyexpertexternal20220923/models/_chat_ref_doc_page_info.py
alibabacloud_energyexpertexternal20220923/models/_chat_ref_doc_page_num.py
alibabacloud_energyexpertexternal20220923/models/_chat_ref_doc_postion.py
alibabacloud_energyexpertexternal20220923-4.4.3.dist-info/LICENSE
alibabacloud_energyexpertexternal20220923-4.4.3.dist-info/METADATA
alibabacloud_energyexpertexternal20220923-4.4.3.dist-info/WHEEL
alibabacloud_energyexpertexternal20220923-4.4.3.dist-info/top_level.txt
alibabacloud_energyexpertexternal20220923-4.4.3.dist-info/RECORD
